Metadata-Version: 1.0
Name: iso639
Version: 0.1.3
Summary: ISO639-2 support for Python.
Home-page: https://github.com/janpipek/iso639-python
Author: Jan Pipek
Author-email: jan.pipek@gmail.com
License: MIT
Platform: UNKNOWN
